disk_cleanup/__init__.py
disk_cleanup/__main__.py
disk_cleanup/py.typed
disk_cleanup-1.0.0.dist-info/LICENSE
disk_cleanup-1.0.0.dist-info/METADATA
disk_cleanup-1.0.0.dist-info/WHEEL
disk_cleanup-1.0.0.dist-info/entry_points.txt
disk_cleanup-1.0.0.dist-info/top_level.txt
disk_cleanup-1.0.0.dist-info/RECORD
