Metadata-Version: 2.2
Name: disk-cleanup
Version: 1.0.0
Summary: A cli utility that sends low disk warning notifications and cleanups.
Author-email: Pradish Bijukchhe <pradish@sandbox.com.np>
License: Copyright (c) 2025 Pradish Bijukchhe
Project-URL: Homepage, https://github.com/sandbox-pokhara/disk-cleanup
Project-URL: Issues, https://github.com/sandbox-pokhara/disk-cleanup/issues
Classifier: Programming Language :: Python :: 3
Requires-Python: >=3
License-File: LICENSE
